pyfonycore/Kernel.py
pyfonycore/KernelTest.py
pyfonycore/_config/config_test.yaml
pyfonycore/bootstrap/bootstrapped_container.py
pyfonycore/bootstrap/config/Config.py
pyfonycore/bootstrap/config/config_factory.py
pyfonycore/bootstrap/config/config_reader.py
pyfonycore/bootstrap/config/raw/allowed_environments_resolver.py
pyfonycore/bootstrap/config/raw/container_init_resolver.py
pyfonycore/bootstrap/config/raw/kernel_class_resolver.py
pyfonycore/bootstrap/config/raw/raw_config_reader.py
pyfonycore/bootstrap/config/raw/root_module_name_resolver.py
pyfonycore/container/PyfonyHook.py
pyfonycore/container/container_init.py
pyfonycore/container/container_init_test.py
pyfonycore/pyproject.py
pyfony_core-0.8.4.dist-info/LICENSE
pyfony_core-0.8.4.dist-info/WHEEL
pyfony_core-0.8.4.dist-info/METADATA
pyfony_core-0.8.4.dist-info/RECORD
